tagkit/__init__.py
tagkit/py.typed
tagkit/cli/__init__.py
tagkit/cli/cli_formatting.py
tagkit/cli/file_resolver.py
tagkit/cli/main.py
tagkit/cli/view.py
tagkit/conf/formatting.yaml
tagkit/conf/registry.yaml
tagkit/core/__init__.py
tagkit/core/exceptions.py
tagkit/core/formatting.py
tagkit/core/registry.py
tagkit/core/tag.py
tagkit/core/types.py
tagkit/core/utils.py
tagkit/image/__init__.py
tagkit/image/collection.py
tagkit/image/exif.py
tagkit/tag_io/base.py
tagkit/tag_io/piexif_io.py
tagkit-0.3.0.dist-info/METADATA
tagkit-0.3.0.dist-info/WHEEL
tagkit-0.3.0.dist-info/entry_points.txt
tagkit-0.3.0.dist-info/licenses/LICENSE
tagkit-0.3.0.dist-info/RECORD
