Metadata-Version: 2.4
Name: tagkit
Version: 0.3.0
Summary: A CLI & Python API for editing EXIF data in photos.
Project-URL: Homepage, https://github.com/rvforest/tagkit
Project-URL: Documentation, https://tagkit.readthedocs.io/
Project-URL: Source, https://github.com/rvforest/tagkit
Project-URL: Issues, https://github.com/rvforest/tagkit/issues
Author-email: Robert Forest <rvforest@gmail.com>
License: MIT License
License-File: LICENSE
Keywords: cli,exif,image,metadata,photo,python
Classifier: Intended Audience :: Developers
Classifier: License :: OSI Approved :: MIT License
Classifier: Operating System :: OS Independent
Classifier: Programming Language :: Python :: 3
Classifier: Programming Language :: Python :: 3.9
Classifier: Programming Language :: Python :: 3.10
Classifier: Programming Language :: Python :: 3.11
Classifier: Programming Language :: Python :: 3.12
Classifier: Programming Language :: Python :: 3.13
Classifier: Topic :: Multimedia :: Graphics
Classifier: Topic :: Software Development :: Libraries :: Python Modules
Classifier: Topic :: Utilities
Requires-Python: >=3.9
Requires-Dist: piexif>=1.1.3
Requires-Dist: pyyaml>=6.0.2
Requires-Dist: rich>=14.0.0
Requires-Dist: typer>=0.15.2
